[{"name":"nostr_dart","qualifiedName":"nostr_dart","href":"nostr_dart/nostr_dart-library.html","kind":8,"overriddenDepth":0,"packageRank":0,"desc":"A Dart Library for making Nostr clients"},{"name":"CloseMessage","qualifiedName":"nostr_dart.CloseMessage","href":"nostr_dart/CloseMessage-class.html","kind":3,"overriddenDepth":0,"packageRank":0,"desc":"Representation of a Nostr CLOSE Message","enclosedBy":{"name":"nostr_dart","kind":8,"href":"nostr_dart/nostr_dart-library.html"}},{"name":"CloseMessage","qualifiedName":"nostr_dart.CloseMessage.CloseMessage","href":"nostr_dart/CloseMessage/CloseMessage.html","kind":2,"overriddenDepth":0,"packageRank":0,"desc":"","enclosedBy":{"name":"CloseMessage","kind":3,"href":"nostr_dart/CloseMessage-class.html"}},{"name":"CloseMessage.fromJson","qualifiedName":"nostr_dart.CloseMessage.fromJson","href":"nostr_dart/CloseMessage/CloseMessage.fromJson.html","kind":2,"overriddenDepth":0,"packageRank":0,"desc":"","enclosedBy":{"name":"CloseMessage","kind":3,"href":"nostr_dart/CloseMessage-class.html"}},{"name":"props","qualifiedName":"nostr_dart.CloseMessage.props","href":"nostr_dart/CloseMessage/props.html","kind":15,"overriddenDepth":0,"packageRank":0,"desc":"The list of properties that will be used to determine whether\ntwo instances are equal.","enclosedBy":{"name":"CloseMessage","kind":3,"href":"nostr_dart/CloseMessage-class.html"}},{"name":"subscriptionId","qualifiedName":"nostr_dart.CloseMessage.subscriptionId","href":"nostr_dart/CloseMessage/subscriptionId.html","kind":15,"overriddenDepth":0,"packageRank":0,"desc":"","enclosedBy":{"name":"CloseMessage","kind":3,"href":"nostr_dart/CloseMessage-class.html"}},{"name":"toJson","qualifiedName":"nostr_dart.CloseMessage.toJson","href":"nostr_dart/CloseMessage/toJson.html","kind":9,"overriddenDepth":1,"packageRank":0,"desc":"","enclosedBy":{"name":"CloseMessage","kind":3,"href":"nostr_dart/CloseMessage-class.html"}},{"name":"type","qualifiedName":"nostr_dart.CloseMessage.type","href":"nostr_dart/CloseMessage/type-constant.html","kind":1,"overriddenDepth":0,"packageRank":0,"desc":"","enclosedBy":{"name":"CloseMessage","kind":3,"href":"nostr_dart/CloseMessage-class.html"}},{"name":"EoseMessage","qualifiedName":"nostr_dart.EoseMessage","href":"nostr_dart/EoseMessage-class.html","kind":3,"overriddenDepth":0,"packageRank":0,"desc":"Representation of a Nostr EOSE Message","enclosedBy":{"name":"nostr_dart","kind":8,"href":"nostr_dart/nostr_dart-library.html"}},{"name":"EoseMessage","qualifiedName":"nostr_dart.EoseMessage.EoseMessage","href":"nostr_dart/EoseMessage/EoseMessage.html","kind":2,"overriddenDepth":0,"packageRank":0,"desc":"","enclosedBy":{"name":"EoseMessage","kind":3,"href":"nostr_dart/EoseMessage-class.html"}},{"name":"EoseMessage.fromJson","qualifiedName":"nostr_dart.EoseMessage.fromJson","href":"nostr_dart/EoseMessage/EoseMessage.fromJson.html","kind":2,"overriddenDepth":0,"packageRank":0,"desc":"","enclosedBy":{"name":"EoseMessage","kind":3,"href":"nostr_dart/EoseMessage-class.html"}},{"name":"props","qualifiedName":"nostr_dart.EoseMessage.props","href":"nostr_dart/EoseMessage/props.html","kind":15,"overriddenDepth":0,"packageRank":0,"desc":"The list of properties that will be used to determine whether\ntwo instances are equal.","enclosedBy":{"name":"EoseMessage","kind":3,"href":"nostr_dart/EoseMessage-class.html"}},{"name":"subscriptionId","qualifiedName":"nostr_dart.EoseMessage.subscriptionId","href":"nostr_dart/EoseMessage/subscriptionId.html","kind":15,"overriddenDepth":0,"packageRank":0,"desc":"","enclosedBy":{"name":"EoseMessage","kind":3,"href":"nostr_dart/EoseMessage-class.html"}},{"name":"toJson","qualifiedName":"nostr_dart.EoseMessage.toJson","href":"nostr_dart/EoseMessage/toJson.html","kind":9,"overriddenDepth":1,"packageRank":0,"desc":"","enclosedBy":{"name":"EoseMessage","kind":3,"href":"nostr_dart/EoseMessage-class.html"}},{"name":"type","qualifiedName":"nostr_dart.EoseMessage.type","href":"nostr_dart/EoseMessage/type-constant.html","kind":1,"overriddenDepth":0,"packageRank":0,"desc":"","enclosedBy":{"name":"EoseMessage","kind":3,"href":"nostr_dart/EoseMessage-class.html"}},{"name":"EventMessage","qualifiedName":"nostr_dart.EventMessage","href":"nostr_dart/EventMessage-class.html","kind":3,"overriddenDepth":0,"packageRank":0,"desc":"Representation of a Nostr EVENT Message","enclosedBy":{"name":"nostr_dart","kind":8,"href":"nostr_dart/nostr_dart-library.html"}},{"name":"EventMessage","qualifiedName":"nostr_dart.EventMessage.EventMessage","href":"nostr_dart/EventMessage/EventMessage.html","kind":2,"overriddenDepth":0,"packageRank":0,"desc":"","enclosedBy":{"name":"EventMessage","kind":3,"href":"nostr_dart/EventMessage-class.html"}},{"name":"calculateEventId","qualifiedName":"nostr_dart.EventMessage.calculateEventId","href":"nostr_dart/EventMessage/calculateEventId.html","kind":9,"overriddenDepth":0,"packageRank":0,"desc":"Calculate event id using a given event data.","enclosedBy":{"name":"EventMessage","kind":3,"href":"nostr_dart/EventMessage-class.html"}},{"name":"content","qualifiedName":"nostr_dart.EventMessage.content","href":"nostr_dart/EventMessage/content.html","kind":15,"overriddenDepth":0,"packageRank":0,"desc":"Arbitrary string.","enclosedBy":{"name":"EventMessage","kind":3,"href":"nostr_dart/EventMessage-class.html"}},{"name":"createdAt","qualifiedName":"nostr_dart.EventMessage.createdAt","href":"nostr_dart/EventMessage/createdAt.html","kind":15,"overriddenDepth":0,"packageRank":0,"desc":"Time when the event is created.","enclosedBy":{"name":"EventMessage","kind":3,"href":"nostr_dart/EventMessage-class.html"}},{"name":"EventMessage.fromData","qualifiedName":"nostr_dart.EventMessage.fromData","href":"nostr_dart/EventMessage/EventMessage.fromData.html","kind":2,"overriddenDepth":0,"packageRank":0,"desc":"","enclosedBy":{"name":"EventMessage","kind":3,"href":"nostr_dart/EventMessage-class.html"}},{"name":"EventMessage.fromJson","qualifiedName":"nostr_dart.EventMessage.fromJson","href":"nostr_dart/EventMessage/EventMessage.fromJson.html","kind":2,"overriddenDepth":0,"packageRank":0,"desc":"","enclosedBy":{"name":"EventMessage","kind":3,"href":"nostr_dart/EventMessage-class.html"}},{"name":"id","qualifiedName":"nostr_dart.EventMessage.id","href":"nostr_dart/EventMessage/id.html","kind":15,"overriddenDepth":0,"packageRank":0,"desc":"32-bytes lowercase hex-encoded sha256 of the serialized event data.","enclosedBy":{"name":"EventMessage","kind":3,"href":"nostr_dart/EventMessage-class.html"}},{"name":"kind","qualifiedName":"nostr_dart.EventMessage.kind","href":"nostr_dart/EventMessage/kind.html","kind":15,"overriddenDepth":0,"packageRank":0,"desc":"Integer between 0 and 65535.","enclosedBy":{"name":"EventMessage","kind":3,"href":"nostr_dart/EventMessage-class.html"}},{"name":"props","qualifiedName":"nostr_dart.EventMessage.props","href":"nostr_dart/EventMessage/props.html","kind":15,"overriddenDepth":0,"packageRank":0,"desc":"The list of properties that will be used to determine whether\ntwo instances are equal.","enclosedBy":{"name":"EventMessage","kind":3,"href":"nostr_dart/EventMessage-class.html"}},{"name":"pubkey","qualifiedName":"nostr_dart.EventMessage.pubkey","href":"nostr_dart/EventMessage/pubkey.html","kind":15,"overriddenDepth":0,"packageRank":0,"desc":"32-bytes lowercase hex-encoded public key of the event creator.","enclosedBy":{"name":"EventMessage","kind":3,"href":"nostr_dart/EventMessage-class.html"}},{"name":"sig","qualifiedName":"nostr_dart.EventMessage.sig","href":"nostr_dart/EventMessage/sig.html","kind":15,"overriddenDepth":0,"packageRank":0,"desc":"64-bytes lowercase hex of the signature of the sha256 hash of the serialized event data,\nwhich is the same as the id field.","enclosedBy":{"name":"EventMessage","kind":3,"href":"nostr_dart/EventMessage-class.html"}},{"name":"subscriptionId","qualifiedName":"nostr_dart.EventMessage.subscriptionId","href":"nostr_dart/EventMessage/subscriptionId.html","kind":15,"overriddenDepth":0,"packageRank":0,"desc":"An arbitrary, non-empty string of max length 64 chars, that should be used to represent a subscription.","enclosedBy":{"name":"EventMessage","kind":3,"href":"nostr_dart/EventMessage-class.html"}},{"name":"tags","qualifiedName":"nostr_dart.EventMessage.tags","href":"nostr_dart/EventMessage/tags.html","kind":15,"overriddenDepth":0,"packageRank":0,"desc":"Each tag is an array of strings of arbitrary size, with some conventions around them.","enclosedBy":{"name":"EventMessage","kind":3,"href":"nostr_dart/EventMessage-class.html"}},{"name":"toJson","qualifiedName":"nostr_dart.EventMessage.toJson","href":"nostr_dart/EventMessage/toJson.html","kind":9,"overriddenDepth":1,"packageRank":0,"desc":"","enclosedBy":{"name":"EventMessage","kind":3,"href":"nostr_dart/EventMessage-class.html"}},{"name":"type","qualifiedName":"nostr_dart.EventMessage.type","href":"nostr_dart/EventMessage/type-constant.html","kind":1,"overriddenDepth":0,"packageRank":0,"desc":"","enclosedBy":{"name":"EventMessage","kind":3,"href":"nostr_dart/EventMessage-class.html"}},{"name":"InvalidEventException","qualifiedName":"nostr_dart.InvalidEventException","href":"nostr_dart/InvalidEventException-class.html","kind":3,"overriddenDepth":0,"packageRank":0,"desc":"","enclosedBy":{"name":"nostr_dart","kind":8,"href":"nostr_dart/nostr_dart-library.html"}},{"name":"InvalidEventException","qualifiedName":"nostr_dart.InvalidEventException.InvalidEventException","href":"nostr_dart/InvalidEventException/InvalidEventException.html","kind":2,"overriddenDepth":0,"packageRank":0,"desc":"","enclosedBy":{"name":"InvalidEventException","kind":3,"href":"nostr_dart/InvalidEventException-class.html"}},{"name":"event","qualifiedName":"nostr_dart.InvalidEventException.event","href":"nostr_dart/InvalidEventException/event.html","kind":15,"overriddenDepth":0,"packageRank":0,"desc":"","enclosedBy":{"name":"InvalidEventException","kind":3,"href":"nostr_dart/InvalidEventException-class.html"}},{"name":"toString","qualifiedName":"nostr_dart.InvalidEventException.toString","href":"nostr_dart/InvalidEventException/toString.html","kind":9,"overriddenDepth":1,"packageRank":0,"desc":"A string representation of this object.","enclosedBy":{"name":"InvalidEventException","kind":3,"href":"nostr_dart/InvalidEventException-class.html"}},{"name":"KeyStore","qualifiedName":"nostr_dart.KeyStore","href":"nostr_dart/KeyStore-class.html","kind":3,"overriddenDepth":0,"packageRank":0,"desc":"Encapsulation of crypto-related tasks.","enclosedBy":{"name":"nostr_dart","kind":8,"href":"nostr_dart/nostr_dart-library.html"}},{"name":"KeyStore.fromPrivate","qualifiedName":"nostr_dart.KeyStore.fromPrivate","href":"nostr_dart/KeyStore/KeyStore.fromPrivate.html","kind":2,"overriddenDepth":0,"packageRank":0,"desc":"Produces the KeyStore from a private key.","enclosedBy":{"name":"KeyStore","kind":3,"href":"nostr_dart/KeyStore-class.html"}},{"name":"KeyStore.generate","qualifiedName":"nostr_dart.KeyStore.generate","href":"nostr_dart/KeyStore/KeyStore.generate.html","kind":2,"overriddenDepth":0,"packageRank":0,"desc":"Produces KeyStore from scratch.","enclosedBy":{"name":"KeyStore","kind":3,"href":"nostr_dart/KeyStore-class.html"}},{"name":"privateKey","qualifiedName":"nostr_dart.KeyStore.privateKey","href":"nostr_dart/KeyStore/privateKey.html","kind":15,"overriddenDepth":0,"packageRank":0,"desc":"32-bytes lowercase hex-encoded private key.\nUsed to decrypt messages and generate message signatures.\nMust be kept secret.","enclosedBy":{"name":"KeyStore","kind":3,"href":"nostr_dart/KeyStore-class.html"}},{"name":"publicKey","qualifiedName":"nostr_dart.KeyStore.publicKey","href":"nostr_dart/KeyStore/publicKey.html","kind":15,"overriddenDepth":0,"packageRank":0,"desc":"32-bytes lowercase hex-encoded public key.\nUsed to encrypt messages and verify signatures.\nCan be shared with anyone.","enclosedBy":{"name":"KeyStore","kind":3,"href":"nostr_dart/KeyStore-class.html"}},{"name":"sign","qualifiedName":"nostr_dart.KeyStore.sign","href":"nostr_dart/KeyStore/sign.html","kind":9,"overriddenDepth":0,"packageRank":0,"desc":"Generates a schnorr signature using the BIP-340 scheme.","enclosedBy":{"name":"KeyStore","kind":3,"href":"nostr_dart/KeyStore-class.html"}},{"name":"toString","qualifiedName":"nostr_dart.KeyStore.toString","href":"nostr_dart/KeyStore/toString.html","kind":9,"overriddenDepth":1,"packageRank":0,"desc":"A string representation of this object.","enclosedBy":{"name":"KeyStore","kind":3,"href":"nostr_dart/KeyStore-class.html"}},{"name":"verifySignature","qualifiedName":"nostr_dart.KeyStore.verifySignature","href":"nostr_dart/KeyStore/verifySignature.html","kind":9,"overriddenDepth":0,"packageRank":0,"desc":"Verifies a schnorr signature using the BIP-340 scheme.","enclosedBy":{"name":"KeyStore","kind":3,"href":"nostr_dart/KeyStore-class.html"}},{"name":"NostrLogLevel","qualifiedName":"nostr_dart.NostrLogLevel","href":"nostr_dart/NostrLogLevel-class.html","kind":3,"overriddenDepth":0,"packageRank":0,"desc":"Logging output level.","enclosedBy":{"name":"nostr_dart","kind":8,"href":"nostr_dart/nostr_dart-library.html"}},{"name":"ALL","qualifiedName":"nostr_dart.NostrLogLevel.ALL","href":"nostr_dart/NostrLogLevel/ALL-constant.html","kind":1,"overriddenDepth":0,"packageRank":0,"desc":"Turn on all levels","enclosedBy":{"name":"NostrLogLevel","kind":3,"href":"nostr_dart/NostrLogLevel-class.html"}},{"name":"INFO","qualifiedName":"nostr_dart.NostrLogLevel.INFO","href":"nostr_dart/NostrLogLevel/INFO-constant.html","kind":1,"overriddenDepth":0,"packageRank":0,"desc":"Informational messages","enclosedBy":{"name":"NostrLogLevel","kind":3,"href":"nostr_dart/NostrLogLevel-class.html"}},{"name":"NostrLogLevel","qualifiedName":"nostr_dart.NostrLogLevel.NostrLogLevel","href":"nostr_dart/NostrLogLevel/NostrLogLevel.html","kind":2,"overriddenDepth":0,"packageRank":0,"desc":"","enclosedBy":{"name":"NostrLogLevel","kind":3,"href":"nostr_dart/NostrLogLevel-class.html"}},{"name":"OFF","qualifiedName":"nostr_dart.NostrLogLevel.OFF","href":"nostr_dart/NostrLogLevel/OFF-constant.html","kind":1,"overriddenDepth":0,"packageRank":0,"desc":"Turn off the logging","enclosedBy":{"name":"NostrLogLevel","kind":3,"href":"nostr_dart/NostrLogLevel-class.html"}},{"name":"WARNING","qualifiedName":"nostr_dart.NostrLogLevel.WARNING","href":"nostr_dart/NostrLogLevel/WARNING-constant.html","kind":1,"overriddenDepth":0,"packageRank":0,"desc":"Potential problems","enclosedBy":{"name":"NostrLogLevel","kind":3,"href":"nostr_dart/NostrLogLevel-class.html"}},{"name":"NostrRelay","qualifiedName":"nostr_dart.NostrRelay","href":"nostr_dart/NostrRelay-class.html","kind":3,"overriddenDepth":0,"packageRank":0,"desc":"A class to represent a Nostr relay.","enclosedBy":{"name":"nostr_dart","kind":8,"href":"nostr_dart/nostr_dart-library.html"}},{"name":"NostrRelay","qualifiedName":"nostr_dart.NostrRelay.NostrRelay","href":"nostr_dart/NostrRelay/NostrRelay.html","kind":2,"overriddenDepth":0,"packageRank":0,"desc":"","enclosedBy":{"name":"NostrRelay","kind":3,"href":"nostr_dart/NostrRelay-class.html"}},{"name":"close","qualifiedName":"nostr_dart.NostrRelay.close","href":"nostr_dart/NostrRelay/close.html","kind":9,"overriddenDepth":0,"packageRank":0,"desc":"Closes the corresponding socket connection.","enclosedBy":{"name":"NostrRelay","kind":3,"href":"nostr_dart/NostrRelay-class.html"}},{"name":"connect","qualifiedName":"nostr_dart.NostrRelay.connect","href":"nostr_dart/NostrRelay/connect.html","kind":9,"overriddenDepth":0,"packageRank":0,"desc":"Creates a new Relay and waits for it to be connected.","enclosedBy":{"name":"NostrRelay","kind":3,"href":"nostr_dart/NostrRelay-class.html"}},{"name":"messages","qualifiedName":"nostr_dart.NostrRelay.messages","href":"nostr_dart/NostrRelay/messages.html","kind":15,"overriddenDepth":0,"packageRank":0,"desc":"Stream of decoded WebSocket's messages","enclosedBy":{"name":"NostrRelay","kind":3,"href":"nostr_dart/NostrRelay-class.html"}},{"name":"sendEvent","qualifiedName":"nostr_dart.NostrRelay.sendEvent","href":"nostr_dart/NostrRelay/sendEvent.html","kind":9,"overriddenDepth":0,"packageRank":0,"desc":"Sends the EventMessage to the Relay and waits for\nan OkMessage with the same eventId.","enclosedBy":{"name":"NostrRelay","kind":3,"href":"nostr_dart/NostrRelay-class.html"}},{"name":"sendMessage","qualifiedName":"nostr_dart.NostrRelay.sendMessage","href":"nostr_dart/NostrRelay/sendMessage.html","kind":9,"overriddenDepth":0,"packageRank":0,"desc":"Sends the RelayMessage to the Relay","enclosedBy":{"name":"NostrRelay","kind":3,"href":"nostr_dart/NostrRelay-class.html"}},{"name":"socket","qualifiedName":"nostr_dart.NostrRelay.socket","href":"nostr_dart/NostrRelay/socket.html","kind":15,"overriddenDepth":0,"packageRank":0,"desc":"Corresponding Relay's WebSocket connection","enclosedBy":{"name":"NostrRelay","kind":3,"href":"nostr_dart/NostrRelay-class.html"}},{"name":"subscribe","qualifiedName":"nostr_dart.NostrRelay.subscribe","href":"nostr_dart/NostrRelay/subscribe.html","kind":9,"overriddenDepth":0,"packageRank":0,"desc":"Sends the provided RequestMessage to the Relay and\nreturns an instance of NostrSubscription that contains\na stream of RelayMessage filtered by the requestMessage's subscriptionId","enclosedBy":{"name":"NostrRelay","kind":3,"href":"nostr_dart/NostrRelay-class.html"}},{"name":"unsubscribe","qualifiedName":"nostr_dart.NostrRelay.unsubscribe","href":"nostr_dart/NostrRelay/unsubscribe.html","kind":9,"overriddenDepth":0,"packageRank":0,"desc":"Closes the previously created NostrSubscription identified by the provided subscriptionId.","enclosedBy":{"name":"NostrRelay","kind":3,"href":"nostr_dart/NostrRelay-class.html"}},{"name":"url","qualifiedName":"nostr_dart.NostrRelay.url","href":"nostr_dart/NostrRelay/url.html","kind":15,"overriddenDepth":0,"packageRank":0,"desc":"URL of the Relay's WebSocket.","enclosedBy":{"name":"NostrRelay","kind":3,"href":"nostr_dart/NostrRelay-class.html"}},{"name":"NostrSubscription","qualifiedName":"nostr_dart.NostrSubscription","href":"nostr_dart/NostrSubscription-class.html","kind":3,"overriddenDepth":0,"packageRank":0,"desc":"A class to represent a Nostr subscription.","enclosedBy":{"name":"nostr_dart","kind":8,"href":"nostr_dart/nostr_dart-library.html"}},{"name":"NostrSubscription","qualifiedName":"nostr_dart.NostrSubscription.NostrSubscription","href":"nostr_dart/NostrSubscription/NostrSubscription.html","kind":2,"overriddenDepth":0,"packageRank":0,"desc":"","enclosedBy":{"name":"NostrSubscription","kind":3,"href":"nostr_dart/NostrSubscription-class.html"}},{"name":"dispose","qualifiedName":"nostr_dart.NostrSubscription.dispose","href":"nostr_dart/NostrSubscription/dispose.html","kind":9,"overriddenDepth":0,"packageRank":0,"desc":"Clean-up method called on subscription cancellation.","enclosedBy":{"name":"NostrSubscription","kind":3,"href":"nostr_dart/NostrSubscription-class.html"}},{"name":"getRenewRequestMessage","qualifiedName":"nostr_dart.NostrSubscription.getRenewRequestMessage","href":"nostr_dart/NostrSubscription/getRenewRequestMessage.html","kind":15,"overriddenDepth":0,"packageRank":0,"desc":"Method to generate a RequestMessage to renew the subscription.","enclosedBy":{"name":"NostrSubscription","kind":3,"href":"nostr_dart/NostrSubscription-class.html"}},{"name":"id","qualifiedName":"nostr_dart.NostrSubscription.id","href":"nostr_dart/NostrSubscription/id.html","kind":15,"overriddenDepth":0,"packageRank":0,"desc":"Arbitrary, non-empty string of max length 64 chars that represents a subscription.","enclosedBy":{"name":"NostrSubscription","kind":3,"href":"nostr_dart/NostrSubscription-class.html"}},{"name":"lastMessageTime","qualifiedName":"nostr_dart.NostrSubscription.lastMessageTime","href":"nostr_dart/NostrSubscription/lastMessageTime.html","kind":15,"overriddenDepth":0,"packageRank":0,"desc":"","enclosedBy":{"name":"NostrSubscription","kind":3,"href":"nostr_dart/NostrSubscription-class.html"}},{"name":"messages","qualifiedName":"nostr_dart.NostrSubscription.messages","href":"nostr_dart/NostrSubscription/messages.html","kind":15,"overriddenDepth":0,"packageRank":0,"desc":"A stream of RelayMessages of the current Subscription.","enclosedBy":{"name":"NostrSubscription","kind":3,"href":"nostr_dart/NostrSubscription-class.html"}},{"name":"requestMessage","qualifiedName":"nostr_dart.NostrSubscription.requestMessage","href":"nostr_dart/NostrSubscription/requestMessage.html","kind":15,"overriddenDepth":0,"packageRank":0,"desc":"A RequestMessage that is used to start the subscription.","enclosedBy":{"name":"NostrSubscription","kind":3,"href":"nostr_dart/NostrSubscription-class.html"}},{"name":"NoticeMessage","qualifiedName":"nostr_dart.NoticeMessage","href":"nostr_dart/NoticeMessage-class.html","kind":3,"overriddenDepth":0,"packageRank":0,"desc":"Representation of a Nostr NOTICE Message","enclosedBy":{"name":"nostr_dart","kind":8,"href":"nostr_dart/nostr_dart-library.html"}},{"name":"NoticeMessage","qualifiedName":"nostr_dart.NoticeMessage.NoticeMessage","href":"nostr_dart/NoticeMessage/NoticeMessage.html","kind":2,"overriddenDepth":0,"packageRank":0,"desc":"","enclosedBy":{"name":"NoticeMessage","kind":3,"href":"nostr_dart/NoticeMessage-class.html"}},{"name":"NoticeMessage.fromJson","qualifiedName":"nostr_dart.NoticeMessage.fromJson","href":"nostr_dart/NoticeMessage/NoticeMessage.fromJson.html","kind":2,"overriddenDepth":0,"packageRank":0,"desc":"","enclosedBy":{"name":"NoticeMessage","kind":3,"href":"nostr_dart/NoticeMessage-class.html"}},{"name":"message","qualifiedName":"nostr_dart.NoticeMessage.message","href":"nostr_dart/NoticeMessage/message.html","kind":15,"overriddenDepth":0,"packageRank":0,"desc":"","enclosedBy":{"name":"NoticeMessage","kind":3,"href":"nostr_dart/NoticeMessage-class.html"}},{"name":"props","qualifiedName":"nostr_dart.NoticeMessage.props","href":"nostr_dart/NoticeMessage/props.html","kind":15,"overriddenDepth":0,"packageRank":0,"desc":"The list of properties that will be used to determine whether\ntwo instances are equal.","enclosedBy":{"name":"NoticeMessage","kind":3,"href":"nostr_dart/NoticeMessage-class.html"}},{"name":"toJson","qualifiedName":"nostr_dart.NoticeMessage.toJson","href":"nostr_dart/NoticeMessage/toJson.html","kind":9,"overriddenDepth":1,"packageRank":0,"desc":"","enclosedBy":{"name":"NoticeMessage","kind":3,"href":"nostr_dart/NoticeMessage-class.html"}},{"name":"type","qualifiedName":"nostr_dart.NoticeMessage.type","href":"nostr_dart/NoticeMessage/type-constant.html","kind":1,"overriddenDepth":0,"packageRank":0,"desc":"","enclosedBy":{"name":"NoticeMessage","kind":3,"href":"nostr_dart/NoticeMessage-class.html"}},{"name":"OkMessage","qualifiedName":"nostr_dart.OkMessage","href":"nostr_dart/OkMessage-class.html","kind":3,"overriddenDepth":0,"packageRank":0,"desc":"Representation of a Nostr OK Message","enclosedBy":{"name":"nostr_dart","kind":8,"href":"nostr_dart/nostr_dart-library.html"}},{"name":"OkMessage","qualifiedName":"nostr_dart.OkMessage.OkMessage","href":"nostr_dart/OkMessage/OkMessage.html","kind":2,"overriddenDepth":0,"packageRank":0,"desc":"","enclosedBy":{"name":"OkMessage","kind":3,"href":"nostr_dart/OkMessage-class.html"}},{"name":"accepted","qualifiedName":"nostr_dart.OkMessage.accepted","href":"nostr_dart/OkMessage/accepted.html","kind":15,"overriddenDepth":0,"packageRank":0,"desc":"","enclosedBy":{"name":"OkMessage","kind":3,"href":"nostr_dart/OkMessage-class.html"}},{"name":"eventId","qualifiedName":"nostr_dart.OkMessage.eventId","href":"nostr_dart/OkMessage/eventId.html","kind":15,"overriddenDepth":0,"packageRank":0,"desc":"","enclosedBy":{"name":"OkMessage","kind":3,"href":"nostr_dart/OkMessage-class.html"}},{"name":"OkMessage.fromJson","qualifiedName":"nostr_dart.OkMessage.fromJson","href":"nostr_dart/OkMessage/OkMessage.fromJson.html","kind":2,"overriddenDepth":0,"packageRank":0,"desc":"","enclosedBy":{"name":"OkMessage","kind":3,"href":"nostr_dart/OkMessage-class.html"}},{"name":"message","qualifiedName":"nostr_dart.OkMessage.message","href":"nostr_dart/OkMessage/message.html","kind":15,"overriddenDepth":0,"packageRank":0,"desc":"","enclosedBy":{"name":"OkMessage","kind":3,"href":"nostr_dart/OkMessage-class.html"}},{"name":"props","qualifiedName":"nostr_dart.OkMessage.props","href":"nostr_dart/OkMessage/props.html","kind":15,"overriddenDepth":0,"packageRank":0,"desc":"The list of properties that will be used to determine whether\ntwo instances are equal.","enclosedBy":{"name":"OkMessage","kind":3,"href":"nostr_dart/OkMessage-class.html"}},{"name":"toJson","qualifiedName":"nostr_dart.OkMessage.toJson","href":"nostr_dart/OkMessage/toJson.html","kind":9,"overriddenDepth":1,"packageRank":0,"desc":"","enclosedBy":{"name":"OkMessage","kind":3,"href":"nostr_dart/OkMessage-class.html"}},{"name":"type","qualifiedName":"nostr_dart.OkMessage.type","href":"nostr_dart/OkMessage/type-constant.html","kind":1,"overriddenDepth":0,"packageRank":0,"desc":"","enclosedBy":{"name":"OkMessage","kind":3,"href":"nostr_dart/OkMessage-class.html"}},{"name":"RelayMessage","qualifiedName":"nostr_dart.RelayMessage","href":"nostr_dart/RelayMessage-class.html","kind":3,"overriddenDepth":0,"packageRank":0,"desc":"The base class for all relay messages.","enclosedBy":{"name":"nostr_dart","kind":8,"href":"nostr_dart/nostr_dart-library.html"}},{"name":"RelayMessage","qualifiedName":"nostr_dart.RelayMessage.RelayMessage","href":"nostr_dart/RelayMessage/RelayMessage.html","kind":2,"overriddenDepth":0,"packageRank":0,"desc":"","enclosedBy":{"name":"RelayMessage","kind":3,"href":"nostr_dart/RelayMessage-class.html"}},{"name":"toJson","qualifiedName":"nostr_dart.RelayMessage.toJson","href":"nostr_dart/RelayMessage/toJson.html","kind":9,"overriddenDepth":0,"packageRank":0,"desc":"","enclosedBy":{"name":"RelayMessage","kind":3,"href":"nostr_dart/RelayMessage-class.html"}},{"name":"toString","qualifiedName":"nostr_dart.RelayMessage.toString","href":"nostr_dart/RelayMessage/toString.html","kind":9,"overriddenDepth":2,"packageRank":0,"desc":"A string representation of this object.","enclosedBy":{"name":"RelayMessage","kind":3,"href":"nostr_dart/RelayMessage-class.html"}},{"name":"RequestFilter","qualifiedName":"nostr_dart.RequestFilter","href":"nostr_dart/RequestFilter-class.html","kind":3,"overriddenDepth":0,"packageRank":0,"desc":"Representation of REQ message filter.","enclosedBy":{"name":"nostr_dart","kind":8,"href":"nostr_dart/nostr_dart-library.html"}},{"name":"RequestFilter","qualifiedName":"nostr_dart.RequestFilter.RequestFilter","href":"nostr_dart/RequestFilter/RequestFilter.html","kind":2,"overriddenDepth":0,"packageRank":0,"desc":"","enclosedBy":{"name":"RequestFilter","kind":3,"href":"nostr_dart/RequestFilter-class.html"}},{"name":"authors","qualifiedName":"nostr_dart.RequestFilter.authors","href":"nostr_dart/RequestFilter/authors.html","kind":15,"overriddenDepth":0,"packageRank":0,"desc":"a list of lowercase pubkeys, the pubkey of an event must be one of these","enclosedBy":{"name":"RequestFilter","kind":3,"href":"nostr_dart/RequestFilter-class.html"}},{"name":"copyWith","qualifiedName":"nostr_dart.RequestFilter.copyWith","href":"nostr_dart/RequestFilter/copyWith.html","kind":9,"overriddenDepth":0,"packageRank":0,"desc":"","enclosedBy":{"name":"RequestFilter","kind":3,"href":"nostr_dart/RequestFilter-class.html"}},{"name":"e","qualifiedName":"nostr_dart.RequestFilter.e","href":"nostr_dart/RequestFilter/e.html","kind":15,"overriddenDepth":0,"packageRank":0,"desc":"a list of event ids","enclosedBy":{"name":"RequestFilter","kind":3,"href":"nostr_dart/RequestFilter-class.html"}},{"name":"RequestFilter.fromJson","qualifiedName":"nostr_dart.RequestFilter.fromJson","href":"nostr_dart/RequestFilter/RequestFilter.fromJson.html","kind":2,"overriddenDepth":0,"packageRank":0,"desc":"","enclosedBy":{"name":"RequestFilter","kind":3,"href":"nostr_dart/RequestFilter-class.html"}},{"name":"ids","qualifiedName":"nostr_dart.RequestFilter.ids","href":"nostr_dart/RequestFilter/ids.html","kind":15,"overriddenDepth":0,"packageRank":0,"desc":"a list of event ids","enclosedBy":{"name":"RequestFilter","kind":3,"href":"nostr_dart/RequestFilter-class.html"}},{"name":"kinds","qualifiedName":"nostr_dart.RequestFilter.kinds","href":"nostr_dart/RequestFilter/kinds.html","kind":15,"overriddenDepth":0,"packageRank":0,"desc":"a list of a kind numbers","enclosedBy":{"name":"RequestFilter","kind":3,"href":"nostr_dart/RequestFilter-class.html"}},{"name":"limit","qualifiedName":"nostr_dart.RequestFilter.limit","href":"nostr_dart/RequestFilter/limit.html","kind":15,"overriddenDepth":0,"packageRank":0,"desc":"maximum number of events relays return in the initial query","enclosedBy":{"name":"RequestFilter","kind":3,"href":"nostr_dart/RequestFilter-class.html"}},{"name":"p","qualifiedName":"nostr_dart.RequestFilter.p","href":"nostr_dart/RequestFilter/p.html","kind":15,"overriddenDepth":0,"packageRank":0,"desc":"a list of event pubkeys","enclosedBy":{"name":"RequestFilter","kind":3,"href":"nostr_dart/RequestFilter-class.html"}},{"name":"props","qualifiedName":"nostr_dart.RequestFilter.props","href":"nostr_dart/RequestFilter/props.html","kind":15,"overriddenDepth":0,"packageRank":0,"desc":"The list of properties that will be used to determine whether\ntwo instances are equal.","enclosedBy":{"name":"RequestFilter","kind":3,"href":"nostr_dart/RequestFilter-class.html"}},{"name":"since","qualifiedName":"nostr_dart.RequestFilter.since","href":"nostr_dart/RequestFilter/since.html","kind":15,"overriddenDepth":0,"packageRank":0,"desc":"an integer unix timestamp in seconds, events must be newer than this to pass","enclosedBy":{"name":"RequestFilter","kind":3,"href":"nostr_dart/RequestFilter-class.html"}},{"name":"toJson","qualifiedName":"nostr_dart.RequestFilter.toJson","href":"nostr_dart/RequestFilter/toJson.html","kind":9,"overriddenDepth":0,"packageRank":0,"desc":"","enclosedBy":{"name":"RequestFilter","kind":3,"href":"nostr_dart/RequestFilter-class.html"}},{"name":"toString","qualifiedName":"nostr_dart.RequestFilter.toString","href":"nostr_dart/RequestFilter/toString.html","kind":9,"overriddenDepth":2,"packageRank":0,"desc":"A string representation of this object.","enclosedBy":{"name":"RequestFilter","kind":3,"href":"nostr_dart/RequestFilter-class.html"}},{"name":"until","qualifiedName":"nostr_dart.RequestFilter.until","href":"nostr_dart/RequestFilter/until.html","kind":15,"overriddenDepth":0,"packageRank":0,"desc":"an integer unix timestamp in seconds, events must be older than this to pass","enclosedBy":{"name":"RequestFilter","kind":3,"href":"nostr_dart/RequestFilter-class.html"}},{"name":"RequestMessage","qualifiedName":"nostr_dart.RequestMessage","href":"nostr_dart/RequestMessage-class.html","kind":3,"overriddenDepth":0,"packageRank":0,"desc":"Representation of Nostr REQ message.","enclosedBy":{"name":"nostr_dart","kind":8,"href":"nostr_dart/nostr_dart-library.html"}},{"name":"RequestMessage","qualifiedName":"nostr_dart.RequestMessage.RequestMessage","href":"nostr_dart/RequestMessage/RequestMessage.html","kind":2,"overriddenDepth":0,"packageRank":0,"desc":"","enclosedBy":{"name":"RequestMessage","kind":3,"href":"nostr_dart/RequestMessage-class.html"}},{"name":"addFilter","qualifiedName":"nostr_dart.RequestMessage.addFilter","href":"nostr_dart/RequestMessage/addFilter.html","kind":9,"overriddenDepth":0,"packageRank":0,"desc":"","enclosedBy":{"name":"RequestMessage","kind":3,"href":"nostr_dart/RequestMessage-class.html"}},{"name":"filters","qualifiedName":"nostr_dart.RequestMessage.filters","href":"nostr_dart/RequestMessage/filters.html","kind":15,"overriddenDepth":0,"packageRank":0,"desc":"","enclosedBy":{"name":"RequestMessage","kind":3,"href":"nostr_dart/RequestMessage-class.html"}},{"name":"RequestMessage.fromJson","qualifiedName":"nostr_dart.RequestMessage.fromJson","href":"nostr_dart/RequestMessage/RequestMessage.fromJson.html","kind":2,"overriddenDepth":0,"packageRank":0,"desc":"","enclosedBy":{"name":"RequestMessage","kind":3,"href":"nostr_dart/RequestMessage-class.html"}},{"name":"props","qualifiedName":"nostr_dart.RequestMessage.props","href":"nostr_dart/RequestMessage/props.html","kind":15,"overriddenDepth":0,"packageRank":0,"desc":"The list of properties that will be used to determine whether\ntwo instances are equal.","enclosedBy":{"name":"RequestMessage","kind":3,"href":"nostr_dart/RequestMessage-class.html"}},{"name":"subscriptionId","qualifiedName":"nostr_dart.RequestMessage.subscriptionId","href":"nostr_dart/RequestMessage/subscriptionId.html","kind":15,"overriddenDepth":0,"packageRank":0,"desc":"arbitrary, non-empty string of max length 64 chars that represents a subscription","enclosedBy":{"name":"RequestMessage","kind":3,"href":"nostr_dart/RequestMessage-class.html"}},{"name":"toJson","qualifiedName":"nostr_dart.RequestMessage.toJson","href":"nostr_dart/RequestMessage/toJson.html","kind":9,"overriddenDepth":1,"packageRank":0,"desc":"","enclosedBy":{"name":"RequestMessage","kind":3,"href":"nostr_dart/RequestMessage-class.html"}},{"name":"toString","qualifiedName":"nostr_dart.RequestMessage.toString","href":"nostr_dart/RequestMessage/toString.html","kind":9,"overriddenDepth":3,"packageRank":0,"desc":"A string representation of this object.","enclosedBy":{"name":"RequestMessage","kind":3,"href":"nostr_dart/RequestMessage-class.html"}},{"name":"type","qualifiedName":"nostr_dart.RequestMessage.type","href":"nostr_dart/RequestMessage/type-constant.html","kind":1,"overriddenDepth":0,"packageRank":0,"desc":"","enclosedBy":{"name":"RequestMessage","kind":3,"href":"nostr_dart/RequestMessage-class.html"}},{"name":"SubscriptionNotFoundException","qualifiedName":"nostr_dart.SubscriptionNotFoundException","href":"nostr_dart/SubscriptionNotFoundException-class.html","kind":3,"overriddenDepth":0,"packageRank":0,"desc":"","enclosedBy":{"name":"nostr_dart","kind":8,"href":"nostr_dart/nostr_dart-library.html"}},{"name":"SubscriptionNotFoundException","qualifiedName":"nostr_dart.SubscriptionNotFoundException.SubscriptionNotFoundException","href":"nostr_dart/SubscriptionNotFoundException/SubscriptionNotFoundException.html","kind":2,"overriddenDepth":0,"packageRank":0,"desc":"","enclosedBy":{"name":"SubscriptionNotFoundException","kind":3,"href":"nostr_dart/SubscriptionNotFoundException-class.html"}},{"name":"subscriptionId","qualifiedName":"nostr_dart.SubscriptionNotFoundException.subscriptionId","href":"nostr_dart/SubscriptionNotFoundException/subscriptionId.html","kind":15,"overriddenDepth":0,"packageRank":0,"desc":"","enclosedBy":{"name":"SubscriptionNotFoundException","kind":3,"href":"nostr_dart/SubscriptionNotFoundException-class.html"}},{"name":"toString","qualifiedName":"nostr_dart.SubscriptionNotFoundException.toString","href":"nostr_dart/SubscriptionNotFoundException/toString.html","kind":9,"overriddenDepth":1,"packageRank":0,"desc":"A string representation of this object.","enclosedBy":{"name":"SubscriptionNotFoundException","kind":3,"href":"nostr_dart/SubscriptionNotFoundException-class.html"}},{"name":"setNostrLogLevel","qualifiedName":"nostr_dart.setNostrLogLevel","href":"nostr_dart/setNostrLogLevel.html","kind":7,"overriddenDepth":0,"packageRank":0,"desc":"Method to set a desired logging output level.","enclosedBy":{"name":"nostr_dart","kind":8,"href":"nostr_dart/nostr_dart-library.html"}}]
